model_helpers/__init__.py
model_helpers/model_helpers.py
model_helpers-0.3.dist-info/METADATA
model_helpers-0.3.dist-info/RECORD
model_helpers-0.3.dist-info/WHEEL
model_helpers-0.3.dist-info/top_level.txt
