Metadata-Version: 2.1
Name: model-helpers
Version: 0.3
Summary: Tools for helping construct/train models
Home-page: https://github.com/bpben/model_helpers
Author: BB
Author-email: yksrotab@gmail.com
License: MIT
Download-URL: https://github.com/bpben/model_helpers/archive/0.1.tar.gz
Keywords: models ML tuning training
Platform: UNKNOWN
Classifier: Development Status :: 3 - Alpha
Classifier: Intended Audience :: Developers
Classifier: License :: OSI Approved :: MIT License
Classifier: Programming Language :: Python :: 3.6
Requires-Python: >=3.6
Requires-Dist: scikit-learn
Requires-Dist: pandas
Requires-Dist: xgboost
